main.py
dongjun_mcp-0.1.0.dist-info/METADATA
dongjun_mcp-0.1.0.dist-info/WHEEL
dongjun_mcp-0.1.0.dist-info/top_level.txt
dongjun_mcp-0.1.0.dist-info/RECORD
